sentry_django_settings/__init__.py
sentry_django_settings/apps.py
sentry_django_settings-0.6.1.dist-info/LICENSE
sentry_django_settings-0.6.1.dist-info/METADATA
sentry_django_settings-0.6.1.dist-info/WHEEL
sentry_django_settings-0.6.1.dist-info/top_level.txt
sentry_django_settings-0.6.1.dist-info/RECORD
